cfbs/VERSION
cfbs/__init__.py
cfbs/__main__.py
cfbs/analyze.py
cfbs/args.py
cfbs/build.py
cfbs/cfbs.1
cfbs/cfbs_config.py
cfbs/cfbs_json.py
cfbs/cfbs_types.py
cfbs/commands.py
cfbs/download.py
cfbs/git.py
cfbs/git_magic.py
cfbs/index.py
cfbs/internal_file_management.py
cfbs/main.py
cfbs/man_generator.py
cfbs/module.py
cfbs/pretty.py
cfbs/prompts.py
cfbs/updates.py
cfbs/utils.py
cfbs/validate.py
cfbs/version.py
cfbs-5.5.1.dist-info/licenses/LICENSE
cfbs-5.5.1.dist-info/METADATA
cfbs-5.5.1.dist-info/WHEEL
cfbs-5.5.1.dist-info/entry_points.txt
cfbs-5.5.1.dist-info/top_level.txt
cfbs-5.5.1.dist-info/RECORD
