Metadata-Version: 2.4
Name: cfbs
Version: 5.5.1
Summary: Tooling to build, manage and deploy CFEngine policy
Home-page: https://github.com/cfengine/cfbs
Author: Northern.tech, Inc.
Author-email: contact@northern.tech
Classifier: Programming Language :: Python :: 3
Classifier: License :: OSI Approved :: MIT License
Classifier: Operating System :: OS Independent
Requires-Python: >=3.5
License-File: LICENSE
Dynamic: author
Dynamic: author-email
Dynamic: classifier
Dynamic: description
Dynamic: description-content-type
Dynamic: home-page
Dynamic: license-file
Dynamic: requires-python
Dynamic: summary
